Workbook

Sheet INPUTS
A1: Precio Premium | B1: Comisión Pasarela | C1: Conversión Freemium | D1: Churn Mensual | E1: CAC | F1: Inversión Inicial | G1: Cargas Sociales | H1: Impuesto Sociedades | I1: Marketing Base Mes 1 | J1: Salario Base Mensual | K1: Costo AWS Base | L1: Oficina | M1: Incremento Mkt Mensual %
A2: 4.99 | B2: 0.03 | C2: 0.1 | D2: 0.05 | E2: 9 | F2: 30000 | G2: 0.33 | H2: 0.25 | I2: 1750 | J2: 2800 | K2: 400 | L2: 300 | M2: 0.035

Sheet FLUJO_24_MESES
A1: Mes | B1: Usuarios Totales | C1: Usuarios Premium | D1: Ingresos Netos | E1: Marketing | F1: Personal | G1: AWS | H1: Oficina | I1: Comisión Pasarela | J1: Beneficio Operativo | K1: Impuestos | L1: Flujo Neto | M1: Reinversión | N1: Flujo Acumulado
A2: 0 | B2: 0 | C2: 0 | D2: 0 | E2: 0 | F2: 0 | G2: 0 | H2: 0 | I2: 0 | J2: 0 | K2: =0 -> 0 | L2: 0 | N2: =-INPUTS!F2 -> -30000
A3: 1 | B3: =(E3/INPUTS!E2) -> 204.16667 | C3: =B3 -> 204.16667 | D3: =C3*INPUTS!A2*(1-INPUTS!B2) -> 988.22792 | E3: =INPUTS!I2*(1+A3*5%) -> 1837.5 | F3: =IF(A3<=12,2800*(1+INPUTS!$G$2),3400*(1+INPUTS!$G$2)) -> 3724 | G3: =INPUTS!$K$2+(B3*0.05) -> 410.20833 | H3: =INPUTS!L2 -> 300 | I3: =C3*INPUTS!$A$2*INPUTS!$B$2 -> 30.56375 | J3: =D3-E3-F3-G3-H3-I3 -> -5314.0442 | K3: =0 -> 0 | L3: =J3-K3 -> -5314.0442 | M3: =IF(N2>0,L3*0.3,0) -> 0 | N3: =N2+(L3-M3) -> -35314.044
A4: 2 | B4: =(B3*(1-INPUTS!$D$2))+(E4/INPUTS!$E$2) -> 407.84722 | C4: =B4 -> 407.84722 | D4: =C4*INPUTS!$A$2*(1-INPUTS!$B$2) -> 1974.1029 | E4: =INPUTS!$I$2*(1+A4*5%) -> 1925 | F4: =IF(A4<=12,2800*(1+INPUTS!$G$2),3400*(1+INPUTS!$G$2)) -> 3724 | G4: =INPUTS!$K$2+(B4*0.05) -> 420.39236 | H4: =INPUTS!$L$2 -> 300 | I4: =C4*INPUTS!$A$2*INPUTS!$B$2 -> 61.054729 | J4: =D4-E4-F4-G4-H4-I4 -> -4456.3442 | K4: =0 -> 0 | L4: =J4-K4 -> -4456.3442 | M4: =IF(N3>0,L4*0.3,0) -> 0 | N4: =N3+(L4-M4) -> -39770.388
A5: 3 | B5: =(B4*(1-INPUTS!$D$2))+(E5/INPUTS!$E$2) -> 611.06597 | C5: =B5 -> 611.06597 | D5: =C5*INPUTS!$A$2*(1-INPUTS!$B$2) -> 2957.7426 | E5: =INPUTS!$I$2*(1+A5*5%) -> 2012.5 | F5: =IF(A5<=12,2800*(1+INPUTS!$G$2),3400*(1+INPUTS!$G$2)) -> 3724 | G5: =INPUTS!$K$2+(B5*0.05) -> 430.5533 | H5: =INPUTS!$L$2 -> 300 | I5: =C5*INPUTS!$A$2*INPUTS!$B$2 -> 91.476576 | J5: =D5-E5-F5-G5-H5-I5 -> -3600.7872 | K5: =0 -> 0 | L5: =J5-K5 -> -3600.7872 | M5: =IF(N4>0,L5*0.3,0) -> 0 | N5: =N4+(L5-M5) -> -43371.176 | P5: ROI acumulado
A6: 4 | B6: =(B5*(1-INPUTS!$D$2))+(E6/INPUTS!$E$2) -> 813.84601 | C6: =B6 -> 813.84601 | D6: =C6*INPUTS!$A$2*(1-INPUTS!$B$2) -> 3939.2588 | E6: =INPUTS!$I$2*(1+A6*5%) -> 2100 | F6: =IF(A6<=12,2800*(1+INPUTS!$G$2),3400*(1+INPUTS!$G$2)) -> 3724 | G6: =INPUTS!$K$2+(B6*0.05) -> 440.6923 | H6: =INPUTS!$L$2 -> 300 | I6: =C6*INPUTS!$A$2*INPUTS!$B$2 -> 121.83275 | J6: =D6-E6-F6-G6-H6-I6 -> -2747.2662 | K6: =0 -> 0 | L6: =J6-K6 -> -2747.2662 | M6: =IF(N5>0,L6*0.3,0) -> 0 | N6: =N5+(L6-M6) -> -46118.442 | P6: =N26/INPUTS!F2 -> 0.98849101
A7: 5 | B7: =(B6*(1-INPUTS!$D$2))+(E7/INPUTS!$E$2) -> 1016.2093 | C7: =B7 -> 1016.2093 | D7: =C7*INPUTS!$A$2*(1-INPUTS!$B$2) -> 4918.7577 | E7: =INPUTS!$I$2*(1+A7*5%) -> 2187.5 | F7: =IF(A7<=12,2800*(1+INPUTS!$G$2),3400*(1+INPUTS!$G$2)) -> 3724 | G7: =INPUTS!$K$2+(B7*0.05) -> 450.81046 | H7: =INPUTS!$L$2 -> 300 | I7: =C7*INPUTS!$A$2*INPUTS!$B$2 -> 152.12653 | J7: =D7-E7-F7-G7-H7-I7 -> -1895.6793 | K7: =0 -> 0 | L7: =J7-K7 -> -1895.6793 | M7: =IF(N6>0,L7*0.3,0) -> 0 | N7: =N6+(L7-M7) -> -48014.121 | P7: Margen Neto Promedio
A8: 6 | B8: =(B7*(1-INPUTS!$D$2))+(E8/INPUTS!$E$2) -> 1218.1766 | C8: =B8 -> 1218.1766 | D8: =C8*INPUTS!$A$2*(1-INPUTS!$B$2) -> 5896.3401 | E8: =INPUTS!$I$2*(1+A8*5%) -> 2275 | F8: =IF(A8<=12,2800*(1+INPUTS!$G$2),3400*(1+INPUTS!$G$2)) -> 3724 | G8: =INPUTS!$K$2+(B8*0.05) -> 460.90883 | H8: =INPUTS!$L$2 -> 300 | I8: =C8*INPUTS!$A$2*INPUTS!$B$2 -> 182.36103 | J8: =D8-E8-F8-G8-H8-I8 -> -1045.9298 | K8: =0 -> 0 | L8: =J8-K8 -> -1045.9298 | M8: =IF(N7>0,L8*0.3,0) -> 0 | N8: =N7+(L8-M8) -> -49060.051 | P8: =AVERAGE(L3:L26)/AVERAGE(D3:D26) -> 0.23612052
A9: 7 | B9: =(B8*(1-INPUTS!$D$2))+(E9/INPUTS!$E$2) -> 1419.7677 | C9: =B9 -> 1419.7677 | D9: =C9*INPUTS!$A$2*(1-INPUTS!$B$2) -> 6872.1018 | E9: =INPUTS!$I$2*(1+A9*5%) -> 2362.5 | F9: =IF(A9<=12,2800*(1+INPUTS!$G$2),3400*(1+INPUTS!$G$2)) -> 3724 | G9: =INPUTS!$K$2+(B9*0.05) -> 470.98839 | H9: =INPUTS!$L$2 -> 300 | I9: =C9*INPUTS!$A$2*INPUTS!$B$2 -> 212.53923 | J9: =D9-E9-F9-G9-H9-I9 -> -197.92579 | K9: =0 -> 0 | L9: =J9-K9 -> -197.92579 | M9: =IF(N8>0,L9*0.3,0) -> 0 | N9: =N8+(L9-M9) -> -49257.977 | P9: Punto de equilibrio
A10: 8 | B10: =(B9*(1-INPUTS!$D$2))+(E10/INPUTS!$E$2) -> 1621.0016 | C10: =B10 -> 1621.0016 | D10: =C10*INPUTS!$A$2*(1-INPUTS!$B$2) -> 7846.134 | E10: =INPUTS!$I$2*(1+A10*5%) -> 2450 | F10: =IF(A10<=12,2800*(1+INPUTS!$G$2),3400*(1+INPUTS!$G$2)) -> 3724 | G10: =INPUTS!$K$2+(B10*0.05) -> 481.05008 | H10: =INPUTS!$L$2 -> 300 | I10: =C10*INPUTS!$A$2*INPUTS!$B$2 -> 242.66394 | J10: =D10-E10-F10-G10-H10-I10 -> 648.41995 | K10: =0 -> 0 | L10: =J10-K10 -> 648.41995 | M10: =IF(N9>0,L10*0.3,0) -> 0 | N10: =N9+(L10-M10) -> -48609.557 | P10: {=MATCH(TRUE,N3:N26>0,0)} -> 20
A11: 9 | B11: =(B10*(1-INPUTS!$D$2))+(E11/INPUTS!$E$2) -> 1821.8959 | C11: =B11 -> 1821.8959 | D11: =C11*INPUTS!$A$2*(1-INPUTS!$B$2) -> 8818.523 | E11: =INPUTS!$I$2*(1+A11*5%) -> 2537.5 | F11: =IF(A11<=12,2800*(1+INPUTS!$G$2),3400*(1+INPUTS!$G$2)) -> 3724 | G11: =INPUTS!$K$2+(B11*0.05) -> 491.0948 | H11: =INPUTS!$L$2 -> 300 | I11: =C11*INPUTS!$A$2*INPUTS!$B$2 -> 272.73782 | J11: =D11-E11-F11-G11-H11-I11 -> 1493.1903 | K11: =0 -> 0 | L11: =J11-K11 -> 1493.1903 | M11: =IF(N10>0,L11*0.3,0) -> 0 | N11: =N10+(L11-M11) -> -47116.366
A12: 10 | B12: =(B11*(1-INPUTS!$D$2))+(E12/INPUTS!$E$2) -> 2022.4678 | C12: =B12 -> 2022.4678 | D12: =C12*INPUTS!$A$2*(1-INPUTS!$B$2) -> 9789.351 | E12: =INPUTS!$I$2*(1+A12*5%) -> 2625 | F12: =IF(A12<=12,2800*(1+INPUTS!$G$2),3400*(1+INPUTS!$G$2)) -> 3724 | G12: =INPUTS!$K$2+(B12*0.05) -> 501.12339 | H12: =INPUTS!$L$2 -> 300 | I12: =C12*INPUTS!$A$2*INPUTS!$B$2 -> 302.76343 | J12: =D12-E12-F12-G12-H12-I12 -> 2336.4642 | K12: =0 -> 0 | L12: =J12-K12 -> 2336.4642 | M12: =IF(N11>0,L12*0.3,0) -> 0 | N12: =N11+(L12-M12) -> -44779.902
A13: 11 | B13: =(B12*(1-INPUTS!$D$2))+(E13/INPUTS!$E$2) -> 2222.7333 | C13: =B13 -> 2222.7333 | D13: =C13*INPUTS!$A$2*(1-INPUTS!$B$2) -> 10758.696 | E13: =INPUTS!$I$2*(1+A13*5%) -> 2712.5 | F13: =IF(A13<=12,2800*(1+INPUTS!$G$2),3400*(1+INPUTS!$G$2)) -> 3724 | G13: =INPUTS!$K$2+(B13*0.05) -> 511.13667 | H13: =INPUTS!$L$2 -> 300 | I13: =C13*INPUTS!$A$2*INPUTS!$B$2 -> 332.74318 | J13: =D13-E13-F13-G13-H13-I13 -> 3178.3162 | K13: =0 -> 0 | L13: =J13-K13 -> 3178.3162 | M13: =IF(N12>0,L13*0.3,0) -> 0 | N13: =N12+(L13-M13) -> -41601.586
A14: 12 | B14: =(B13*(1-INPUTS!$D$2))+(E14/INPUTS!$E$2) -> 2422.7078 | C14: =B14 -> 2422.7078 | D14: =C14*INPUTS!$A$2*(1-INPUTS!$B$2) -> 11726.632 | E14: =INPUTS!$I$2*(1+A14*5%) -> 2800 | F14: =IF(A14<=12,2800*(1+INPUTS!$G$2),3400*(1+INPUTS!$G$2)) -> 3724 | G14: =INPUTS!$K$2+(B14*0.05) -> 521.13539 | H14: =INPUTS!$L$2 -> 300 | I14: =C14*INPUTS!$A$2*INPUTS!$B$2 -> 362.67935 | J14: =D14-E14-F14-G14-H14-I14 -> 4018.8176 | K14: =IF(SUM(J3:J14)>0,SUM(J3:J14)*INPUTS!$H$2,0) -> 0 | L14: =J14-K14 -> 4018.8176 | M14: =IF(N13>0,L14*0.3,0) -> 0 | N14: =N13+(L14-M14) -> -37582.768
A15: 13 | B15: =(B14*(1-INPUTS!$D$2))+(E15/INPUTS!$E$2) -> 2622.4057 | C15: =B15 -> 2622.4057 | D15: =C15*INPUTS!$A$2*(1-INPUTS!$B$2) -> 12693.23 | E15: =INPUTS!$I$2*(1+A15*5%) -> 2887.5 | F15: =IF(A15<=12,2800*(1+INPUTS!$G$2),3400*(1+INPUTS!$G$2)) -> 4522 | G15: =INPUTS!$K$2+(B15*0.05) -> 531.12029 | H15: =INPUTS!$L$2 -> 300 | I15: =C15*INPUTS!$A$2*INPUTS!$B$2 -> 392.57413 | J15: =D15-E15-F15-G15-H15-I15 -> 4060.0359 | K15: 0 | L15: =J15-K15 -> 4060.0359 | M15: =IF(N14>0,L15*0.3,0) -> 0 | N15: =N14+(L15-M15) -> -33522.732
A16: 14 | B16: =(B15*(1-INPUTS!$D$2))+(E16/INPUTS!$E$2) -> 2821.841 | C16: =B16 -> 2821.841 | D16: =C16*INPUTS!$A$2*(1-INPUTS!$B$2) -> 13658.557 | E16: =INPUTS!$I$2*(1+A16*5%) -> 2975 | F16: =IF(A16<=12,2800*(1+INPUTS!$G$2),3400*(1+INPUTS!$G$2)) -> 4522 | G16: =INPUTS!$K$2+(B16*0.05) -> 541.09205 | H16: =INPUTS!$L$2 -> 300 | I16: =C16*INPUTS!$A$2*INPUTS!$B$2 -> 422.42959 | J16: =D16-E16-F16-G16-H16-I16 -> 4898.0352 | K16: =0 -> 0 | L16: =J16-K16 -> 4898.0352 | M16: =IF(N15>0,L16*0.3,0) -> 0 | N16: =N15+(L16-M16) -> -28624.697
A17: 15 | B17: =(B16*(1-INPUTS!$D$2))+(E17/INPUTS!$E$2) -> 3021.0267 | C17: =B17 -> 3021.0267 | D17: =C17*INPUTS!$A$2*(1-INPUTS!$B$2) -> 14622.676 | E17: =INPUTS!$I$2*(1+A17*5%) -> 3062.5 | F17: =IF(A17<=12,2800*(1+INPUTS!$G$2),3400*(1+INPUTS!$G$2)) -> 4522 | G17: =INPUTS!$K$2+(B17*0.05) -> 551.05134 | H17: =INPUTS!$L$2 -> 300 | I17: =C17*INPUTS!$A$2*INPUTS!$B$2 -> 452.2477 | J17: =D17-E17-F17-G17-H17-I17 -> 5734.8765 | K17: =IF(MOD(A5,3)=0, MAX(0,SUM(J17:J19)*INPUTS!$H$2), 0) -> 4927.702 | L17: =J17-K17 -> 807.17453 | M17: =IF(N16>0,L17*0.3,0) -> 0 | N17: =N16+(L17-M17) -> -27817.523
A18: 16 | B18: =(B17*(1-INPUTS!$D$2))+(E18/INPUTS!$E$2) -> 3219.9754 | C18: =B18 -> 3219.9754 | D18: =C18*INPUTS!$A$2*(1-INPUTS!$B$2) -> 15585.647 | E18: =INPUTS!$I$2*(1+A18*5%) -> 3150 | F18: =IF(A18<=12,2800*(1+INPUTS!$G$2),3400*(1+INPUTS!$G$2)) -> 4522 | G18: =INPUTS!$K$2+(B18*0.05) -> 560.99877 | H18: =INPUTS!$L$2 -> 300 | I18: =C18*INPUTS!$A$2*INPUTS!$B$2 -> 482.03031 | J18: =D18-E18-F18-G18-H18-I18 -> 6570.6177 | K18: =0 -> 0 | L18: =J18-K18 -> 6570.6177 | M18: =IF(N17>0,L18*0.3,0) -> 0 | N18: =N17+(L18-M18) -> -21246.905
A19: 17 | B19: =(B18*(1-INPUTS!$D$2))+(E19/INPUTS!$E$2) -> 3418.6988 | C19: =B19 -> 3418.6988 | D19: =C19*INPUTS!$A$2*(1-INPUTS!$B$2) -> 16547.528 | E19: =INPUTS!$I$2*(1+A19*5%) -> 3237.5 | F19: =IF(A19<=12,2800*(1+INPUTS!$G$2),3400*(1+INPUTS!$G$2)) -> 4522 | G19: =INPUTS!$K$2+(B19*0.05) -> 570.93494 | H19: =INPUTS!$L$2 -> 300 | I19: =C19*INPUTS!$A$2*INPUTS!$B$2 -> 511.77921 | J19: =D19-E19-F19-G19-H19-I19 -> 7405.3138 | K19: =0 -> 0 | L19: =J19-K19 -> 7405.3138 | M19: =IF(N18>0,L19*0.3,0) -> 0 | N19: =N18+(L19-M19) -> -13841.591
A20: 18 | B20: =(B19*(1-INPUTS!$D$2))+(E20/INPUTS!$E$2) -> 3617.2083 | C20: =B20 -> 3617.2083 | D20: =C20*INPUTS!$A$2*(1-INPUTS!$B$2) -> 17508.373 | E20: =INPUTS!$I$2*(1+A20*5%) -> 3325 | F20: =IF(A20<=12,2800*(1+INPUTS!$G$2),3400*(1+INPUTS!$G$2)) -> 4522 | G20: =INPUTS!$K$2+(B20*0.05) -> 580.86042 | H20: =INPUTS!$L$2 -> 300 | I20: =C20*INPUTS!$A$2*INPUTS!$B$2 -> 541.49609 | J20: =D20-E20-F20-G20-H20-I20 -> 8239.017 | K20: =IF(MOD(A5,3)=0, MAX(0,SUM(J18:J20)*INPUTS!$H$2), 0) -> 5553.7371 | L20: =J20-K20 -> 2685.2799 | M20: =IF(N19>0,L20*0.3,0) -> 0 | N20: =N19+(L20-M20) -> -11156.311
A21: 19 | B21: =(B20*(1-INPUTS!$D$2))+(E21/INPUTS!$E$2) -> 3815.5146 | C21: =B21 -> 3815.5146 | D21: =C21*INPUTS!$A$2*(1-INPUTS!$B$2) -> 18468.235 | E21: =INPUTS!$I$2*(1+A21*5%) -> 3412.5 | F21: =IF(A21<=12,2800*(1+INPUTS!$G$2),3400*(1+INPUTS!$G$2)) -> 4522 | G21: =INPUTS!$K$2+(B21*0.05) -> 590.77573 | H21: =INPUTS!$L$2 -> 300 | I21: =C21*INPUTS!$A$2*INPUTS!$B$2 -> 571.18253 | J21: =D21-E21-F21-G21-H21-I21 -> 9071.7769 | K21: =0 -> 0 | L21: =J21-K21 -> 9071.7769 | M21: =IF(N20>0,L21*0.5,0) -> 0 | N21: =N20+(L21-M21) -> -2084.5344
A22: 20 | B22: =(B21*(1-INPUTS!$D$2))+(E22/INPUTS!$E$2) -> 4013.6277 | C22: =B22 -> 4013.6277 | D22: =C22*INPUTS!$A$2*(1-INPUTS!$B$2) -> 19427.162 | E22: =INPUTS!$I$2*(1+A22*5%) -> 3500 | F22: =IF(A22<=12,2800*(1+INPUTS!$G$2),3400*(1+INPUTS!$G$2)) -> 4522 | G22: =INPUTS!$K$2+(B22*0.05) -> 600.68139 | H22: =INPUTS!$L$2 -> 300 | I22: =C22*INPUTS!$A$2*INPUTS!$B$2 -> 600.84007 | J22: =D22-E22-F22-G22-H22-I22 -> 9903.6409 | K22: =0 -> 0 | L22: =J22-K22 -> 9903.6409 | M22: =IF(N21>0,L22*0.3,0) -> 0 | N22: =N21+(L22-M22) -> 7819.1064
A23: 21 | B23: =(B22*(1-INPUTS!$D$2))+(E23/INPUTS!$E$2) -> 4211.5575 | C23: =B23 -> 4211.5575 | D23: =C23*INPUTS!$A$2*(1-INPUTS!$B$2) -> 20385.202 | E23: =INPUTS!$I$2*(1+A23*5%) -> 3587.5 | F23: =IF(A23<=12,2800*(1+INPUTS!$G$2),3400*(1+INPUTS!$G$2)) -> 4522 | G23: =INPUTS!$K$2+(B23*0.05) -> 610.57787 | H23: =INPUTS!$L$2 -> 300 | I23: =C23*INPUTS!$A$2*INPUTS!$B$2 -> 630.47015 | J23: =D23-E23-F23-G23-H23-I23 -> 10734.654 | K23: =IF(MOD(A5,3)=0, MAX(0,SUM(J21:J23)*INPUTS!$H$2), 0) -> 7427.5178 | L23: =J23-K23 -> 3307.1357 | M23: =IF(N22>0,L23*0.3,0) -> 992.14071 | N23: =N22+(L23-M23) -> 10134.101
A24: 22 | B24: =(B23*(1-INPUTS!$D$2))+(E24/INPUTS!$E$2) -> 4409.3129 | C24: =B24 -> 4409.3129 | D24: =C24*INPUTS!$A$2*(1-INPUTS!$B$2) -> 21342.397 | E24: =INPUTS!$I$2*(1+A24*5%) -> 3675 | F24: =IF(A24<=12,2800*(1+INPUTS!$G$2),3400*(1+INPUTS!$G$2)) -> 4522 | G24: =INPUTS!$K$2+(B24*0.05) -> 620.46565 | H24: =INPUTS!$L$2 -> 300 | I24: =C24*INPUTS!$A$2*INPUTS!$B$2 -> 660.07414 | J24: =D24-E24-F24-G24-H24-I24 -> 11564.858 | K24: =0 -> 0 | L24: =J24-K24 -> 11564.858 | M24: =IF(N23>0,L24*0.3,0) -> 3469.4573 | N24: =N23+(L24-M24) -> 18229.502
A25: 23 | B25: =(B24*(1-INPUTS!$D$2))+(E25/INPUTS!$E$2) -> 4606.9028 | C25: =B25 -> 4606.9028 | D25: =C25*INPUTS!$A$2*(1-INPUTS!$B$2) -> 22298.792 | E25: =INPUTS!$I$2*(1+A25*5%) -> 3762.5 | F25: =IF(A25<=12,2800*(1+INPUTS!$G$2),3400*(1+INPUTS!$G$2)) -> 4522 | G25: =INPUTS!$K$2+(B25*0.05) -> 630.34514 | H25: =INPUTS!$L$2 -> 300 | I25: =C25*INPUTS!$A$2*INPUTS!$B$2 -> 689.65335 | J25: =D25-E25-F25-G25-H25-I25 -> 12394.293 | K25: =0 -> 0 | L25: =J25-K25 -> 12394.293 | M25: =IF(N24>0,L25*0.3,0) -> 3718.288 | N25: =N24+(L25-M25) -> 26905.507
A26: 24 | B26: =(B25*(1-INPUTS!$D$2))+(E26/INPUTS!$E$2) -> 4804.3355 | C26: =B26 -> 4804.3355 | D26: =C26*INPUTS!$A$2*(1-INPUTS!$B$2) -> 23254.425 | E26: =INPUTS!$I$2*(1+A26*5%) -> 3850 | F26: =IF(A26<=12,2800*(1+INPUTS!$G$2),3400*(1+INPUTS!$G$2)) -> 4522 | G26: =INPUTS!$K$2+(B26*0.05) -> 640.21677 | H26: =INPUTS!$L$2 -> 300 | I26: =C26*INPUTS!$A$2*INPUTS!$B$2 -> 719.20902 | J26: =D26-E26-F26-G26-H26-I26 -> 13222.999 | K26: =IF(MOD(A5,3)=0, MAX(0,SUM(J24:J26)*INPUTS!$H$2), 0) -> 9295.5375 | L26: =J26-K26 -> 3927.4617 | M26: =IF(N25>0,L26*0.3,0) -> 1178.2385 | N26: =N25+(L26-M26) -> 29654.73

Sheet FLUJO_2_ANIOS
A1: Flujo de caja basado en modelo SASS
A2: Periodo | B2: Usuarios Totales | C2: Usuarios Premium | D2: Ingresos Netos | E2: Marketing | F2: Personal | G2: AWS | H2: Oficina | I2: Comisión Pasarela | J2: Beneficio Operativo | K2: Impuestos | L2: Flujo Neto | M2: Reinversión | N2: Flujo Acumulado
A3: Año 1 | B3: =FLUJO_24_MESES!B14*10 -> 24227.078 | C3: =FLUJO_24_MESES!C14 -> 2422.7078 | D3: =SUM(FLUJO_24_MESES!D3:D14) -> 76485.868 | E3: =SUM(FLUJO_24_MESES!E3:E14) -> 27825 | F3: =SUM(FLUJO_24_MESES!F3:F14) -> 44688 | G3: =SUM(FLUJO_24_MESES!G3:G14) -> 5590.0943 | H3: =SUM(FLUJO_24_MESES!H3:H14) -> 3600 | I3: =SUM(FLUJO_24_MESES!I3:I14) -> 2365.5423 | J3: =SUM(FLUJO_24_MESES!J3:J14) -> -7582.7684 | K3: =SUM(FLUJO_24_MESES!K3:K14) -> 0 | L3: =SUM(FLUJO_24_MESES!L3:L14) -> -7582.7684 | N3: =N3 -> 0
A4: Año 2 | B4: =FLUJO_24_MESES!B26*10 -> 48043.355 | C4: =FLUJO_24_MESES!C26 -> 4804.3355 | D4: =SUM(FLUJO_24_MESES!D15:D26) -> 215792.22 | E4: =SUM(FLUJO_24_MESES!E15:E26) -> 40425 | F4: =SUM(FLUJO_24_MESES!F15:F26) -> 54264 | G4: =SUM(FLUJO_24_MESES!G15:G26) -> 7029.1203 | H4: =SUM(FLUJO_24_MESES!H15:H26) -> 3600 | I4: =SUM(FLUJO_24_MESES!I15:I26) -> 6673.9863 | J4: =SUM(FLUJO_24_MESES!J15:J26) -> 103800.12 | K4: =SUM(FLUJO_24_MESES!K15:K26) -> 27204.494 | ... M4: =SUM(FLUJO_24_MESES!M15:M26) -> 9358.1245 | N4: =FLUJO_24_MESES!N26 -> 29654.73
A6: Indicadores KPI
A7: Indicador | B7: Fórmula
A8: ROI Acumulado | B8: =FLUJO_24_MESES!N26/INPUTS!F2 -> 0.98849101
A9: Margen Promedio | B9: =SUM(FLUJO_24_MESES!J3:J26)/SUM(FLUJO_24_MESES!D3:D26) -> 0.32919795
A10: Punto Equilibrio | B10: =FLUJO_24_MESES!P10 -> 20

Sheet Resumen KPI
C2: 1. Resumen Financiero
C3: Indicador | D3: Año 1 | E3: Año 2
C4: Ingresos Netos | D4: =SUM(FLUJO_24_MESES!D3:D14) -> 76485.868 | E4: =SUM(FLUJO_24_MESES!D15:D26) -> 215792.22
C5: Gastos Operativos | D5: =SUM(FLUJO_2_ANIOS!E3:I3) -> 84068.637 | E5: =SUM(FLUJO_2_ANIOS!E4:I4) -> 111992.11
C6: Beneficio Operativo | D6: =D4-D5 -> -7582.7684 | E6: =E4-E5 -> 103800.12
C7: Impuesto (25%) | D7: =IF(D6>0, D6*0.25, 0) -> 0 | E7: =IF(E6>0, E6*0.25, 0) -> 25950.029
C8: Flujo Neto | D8: =D6+D7 -> -7582.7684 | E8: =E6-E7 -> 77850.088
C9: Flujo Acumulado | D9: =FLUJO_24_MESES!M14 -> 0 | E9: =FLUJO_24_MESES!N26 -> 29654.73
C12: 2. Indicadores de Rentabilidad
C14: Indicador | D14: Año 1 | E14: Año 2
C15: Margen Operativo | D15: =D6/D4 -> -0.099139469 | E15: =E6/E4 -> 0.4810188
C16: Margen Neto | D16: =D8/D4 -> -0.099139469 | E16: =E8/E4 -> 0.3607641
C17: ROI acumulado (sobre 30.000 €) | D17: =D9/INPUTS!$F$2 -> 0 | E17: =E9/INPUTS!$F$2 -> 0.98849101
C18: Punto de Equilibrio | D18: 0 | E18: =FLUJO_24_MESES!$P$10 -> 20
C20: 3. Indicadores Operativos Clave
C22: Indicador | D22: Año 1 | E22: Año 2
C23: Usuarios Premium | D23: =FLUJO_2_ANIOS!C3 -> 2422.7078 | E23: =FLUJO_2_ANIOS!C4 -> 4804.3355
C24: CAC (Coste Adquisición Cliente) | D24: =INPUTS!$E$2 -> 9 | E24: =INPUTS!$E$2 -> 9
C25: Churn Mensual | D25: =INPUTS!$D$2 -> 0.05 | E25: =INPUTS!$D$2 -> 0.05
C26: ARPU Mensual | D26: =INPUTS!$A$2 -> 4.99 | E26: =INPUTS!$A$2 -> 4.99

Sheet KPI final
B4: KPI final del proyecto
B6: Indicador | C6: Resultado Final (24 meses)
B7: ROI total | C7: =FLUJO_24_MESES!P6 -> 0.98849101
B8: ROI anualizado | C8: =(1 + C7)^(1/2) - 1 -> 0.41013865
B9: Margen promedio | C9: =FLUJO_24_MESES!P8 -> 0.23612052
B10: Punto de equilibrio operativo | C10: 8
B11: Punto equilibrio financiero | C11: =FLUJO_24_MESES!P10 -> 20
